{"shipment":[{"carrier_name":"ALLIED O/N EXP","consignment_number":"consAUBW305965797_0","no_of_parcels":2,"shipment_lines":{"shipment_line":[{"order_line_id":0,"product_code":"81546","rejected_quantity":0,"shipped_quantity":1}]},"shipped_date":"2021-06-30 12:09:00","tracking_number":"TMV161037","tracking_url":"https://track.aftership.com/trackings?courier=alliedexpress&tracking-numbers=TMV161037&tracking_postal_code=5114"},{"carrier_name":"ALLIED O/N EXP","consignment_number":"consAUBW306068563_1","no_of_parcels":2,"shipment_lines":{"shipment_line":[{"order_line_id":1,"product_code":"81527","rejected_quantity":0,"shipped_quantity":1}]},"shipped_date":"2021-06-30 12:51:00","tracking_number":"TMV161078","tracking_url":"https://track.aftership.com/trackings?courier=alliedexpress&tracking-numbers=TMV161078&tracking_postal_code=2259"},{"carrier_name":"ALLIED O/N EXP","consignment_number":"consAUBW306140309_1","no_of_parcels":2,"shipment_lines":{"shipment_line":[{"order_line_id":0,"product_code":"81527","rejected_quantity":0,"shipped_quantity":1}]},"shipped_date":"2021-06-30 10:34:00","tracking_number":"TMV161013","tracking_url":"https://track.aftership.com/trackings?courier=alliedexpress&tracking-numbers=TMV161013&tracking_postal_code=2042"},{"carrier_name":"ALLIED O/N EXP","consignment_number":"consAUBW306289906_0","no_of_parcels":1,"shipment_lines":{"shipment_line":[{"order_line_id":0,"product_code":"81544","rejected_quantity":0,"shipped_quantity":1}]},"shipped_date":"2021-06-30 10:30:00","tracking_number":"TMV160985","tracking_url":"https://track.aftership.com/trackings?courier=alliedexpress&tracking-numbers=TMV160985&tracking_postal_code=2225"},{"carrier_name":"ALLIED O/N EXP","consignment_number":"consAUBW306303195_0","no_of_parcels":1,"shipment_lines":{"shipment_line":[{"order_line_id":0,"product_code":"81544","rejected_quantity":0,"shipped_quantity":1}]},"shipped_date":"2021-06-30 10:34:00","tracking_number":"TMV161011","tracking_url":"https://track.aftership.com/trackings?courier=alliedexpress&tracking-numbers=TMV161011&tracking_postal_code=2557"},{"carrier_name":"ALLIED O/N EXP","consignment_number":"consAUBW306312467_0","no_of_parcels":2,"shipment_lines":{"shipment_line":[{"order_line_id":0,"product_code":"81546","rejected_quantity":0,"shipped_quantity":1}]},"shipped_date":"2021-06-30 10:36:00","tracking_number":"TMV161022","tracking_url":"https://track.aftership.com/trackings?courier=alliedexpress&tracking-numbers=TMV161022&tracking_postal_code=2747"},{"carrier_name":"ALLIED O/N EXP","consignment_number":"consAUBW306317534_0","no_of_parcels":2,"shipment_lines":{"shipment_line":[{"order_line_id":0,"product_code":"81546","rejected_quantity":0,"shipped_quantity":1}]},"shipped_date":"2021-06-30 10:35:00","tracking_number":"TMV161015","tracking_url":"https://track.aftership.com/trackings?courier=alliedexpress&tracking-numbers=TMV161015&tracking_postal_code=2769"},{"carrier_name":"ALLIED O/N EXP","consignment_number":"consAUBW306321398_0","no_of_parcels":1,"shipment_lines":{"shipment_line":[{"order_line_id":0,"product_code":"81544","rejected_quantity":0,"shipped_quantity":1}]},"shipped_date":"2021-06-30 12:49:00","tracking_number":"TMV161067","tracking_url":"https://track.aftership.com/trackings?courier=alliedexpress&tracking-numbers=TMV161067&tracking_postal_code=2485"},{"carrier_name":"ALLIED O/N EXP","consignment_number":"consAUBW306333403_0","no_of_parcels":1,"shipment_lines":{"shipment_line":[{"order_line_id":0,"product_code":"81544","rejected_quantity":0,"shipped_quantity":1}]},"shipped_date":"2021-06-30 10:33:00","tracking_number":"TMV161005","tracking_url":"https://track.aftership.com/trackings?courier=alliedexpress&tracking-numbers=TMV161005&tracking_postal_code=2448"},{"carrier_name":"ALLIED O/N EXP","consignment_number":"consAUBW306339121_0","no_of_parcels":1,"shipment_lines":{"shipment_line":[{"order_line_id":0,"product_code":"81529","rejected_quantity":0,"shipped_quantity":1}]},"shipped_date":"2021-06-30 15:06:00","tracking_number":"TMV161130","tracking_url":"https://track.aftership.com/trackings?courier=alliedexpress&tracking-numbers=TMV161130&tracking_postal_code=3212"},{"carrier_name":"ALLIED O/N EXP","consignment_number":"consAUBW306341366_0","no_of_parcels":1,"shipment_lines":{"shipment_line":[{"order_line_id":0,"product_code":"81544","rejected_quantity":0,"shipped_quantity":1}]},"shipped_date":"2021-06-30 12:50:00","tracking_number":"TMV161068","tracking_url":"https://track.aftership.com/trackings?courier=alliedexpress&tracking-numbers=TMV161068&tracking_postal_code=2170"},{"carrier_name":"ALLIED O/N EXP","consignment_number":"consAUBW306348981_0","no_of_parcels":1,"shipment_lines":{"shipment_line":[{"order_line_id":0,"product_code":"81529","rejected_quantity":0,"shipped_quantity":1}]},"shipped_date":"2021-06-30 10:30:00","tracking_number":"TMV160987","tracking_url":"https://track.aftership.com/trackings?courier=alliedexpress&tracking-numbers=TMV160987&tracking_postal_code=2560"},{"carrier_name":"ALLIED O/N EXP","consignment_number":"consAUBW306349012_0","no_of_parcels":1,"shipment_lines":{"shipment_line":[{"order_line_id":2,"product_code":"81529","rejected_quantity":0,"shipped_quantity":1}]},"shipped_date":"2021-06-30 10:36:00","tracking_number":"TMV161020","tracking_url":"https://track.aftership.com/trackings?courier=alliedexpress&tracking-numbers=TMV161020&tracking_postal_code=2750"},{"carrier_name":"ALLIED O/N EXP","consignment_number":"consAUBW306351463_0","no_of_parcels":2,"shipment_lines":{"shipment_line":[{"order_line_id":0,"product_code":"81546","rejected_quantity":0,"shipped_quantity":1}]},"shipped_date":"2021-06-30 10:36:00","tracking_number":"TMV161021","tracking_url":"https://track.aftership.com/trackings?courier=alliedexpress&tracking-numbers=TMV161021&tracking_postal_code=2762"},{"carrier_name":"ALLIED O/N EXP","consignment_number":"consAUBW306353572_0","no_of_parcels":2,"shipment_lines":{"shipment_line":[{"order_line_id":0,"product_code":"81546","rejected_quantity":0,"shipped_quantity":1}]},"shipped_date":"2021-06-30 15:07:00","tracking_number":"TMV161135","tracking_url":"https://track.aftership.com/trackings?courier=alliedexpress&tracking-numbers=TMV161135&tracking_postal_code=3757"},{"carrier_name":"ALLIED O/N EXP","consignment_number":"consAUBW306354663_0","no_of_parcels":1,"shipment_lines":{"shipment_line":[{"order_line_id":0,"product_code":"81544","rejected_quantity":0,"shipped_quantity":1}]},"shipped_date":"2021-06-30 15:08:00","tracking_number":"TMV161139","tracking_url":"https://track.aftership.com/trackings?courier=alliedexpress&tracking-numbers=TMV161139&tracking_postal_code=3754"},{"carrier_name":"AUSTRALIA POST","consignment_number":"consAUBW306270096_0","no_of_parcels":1,"shipment_lines":{"shipment_line":[{"order_line_id":0,"product_code":"121009","rejected_quantity":0,"shipped_quantity":1}]},"shipped_date":"2021-06-30 10:00:00","tracking_number":"89U2038100","tracking_url":"https://auspost.com.au/mypost/track/#/details/89U2038100"},{"carrier_name":"AUSTRALIA POST","consignment_number":"consAUBW306366621_1","no_of_parcels":1,"shipment_lines":{"shipment_line":[{"order_line_id":4,"product_code":"121007","rejected_quantity":0,"shipped_quantity":1}]},"shipped_date":"2021-06-30 09:59:00","tracking_number":"89U2038097","tracking_url":"https://auspost.com.au/mypost/track/#/details/89U2038097"},{"carrier_name":"AUSTRALIA POST","consignment_number":"consAUBW306371482_2","no_of_parcels":1,"shipment_lines":{"shipment_line":[{"order_line_id":6,"product_code":"121014","rejected_quantity":0,"shipped_quantity":1}]},"shipped_date":"2021-06-30 09:57:00","tracking_number":"89U2038087","tracking_url":"https://auspost.com.au/mypost/track/#/details/89U2038087"},{"carrier_name":"AUSTRALIA POST","consignment_number":"consAUBW306373994_0","no_of_parcels":1,"shipment_lines":{"shipment_line":[{"order_line_id":0,"product_code":"121009","rejected_quantity":0,"shipped_quantity":1}]},"shipped_date":"2021-06-30 09:59:00","tracking_number":"89U2038095","tracking_url":"https://auspost.com.au/mypost/track/#/details/89U2038095"},{"carrier_name":"AUSTRALIA POST","consignment_number":"consAUBW306388424_0","no_of_parcels":3,"shipment_lines":{"shipment_line":[{"order_line_id":0,"product_code":"121013","rejected_quantity":0,"shipped_quantity":3}]},"shipped_date":"2021-06-30 09:56:00","tracking_number":"89U2038081","tracking_url":"https://auspost.com.au/mypost/track/#/details/89U2038081"},{"carrier_name":"AUSTRALIA POST","consignment_number":"consAUBW306398412_0","no_of_parcels":1,"shipment_lines":{"shipment_line":[{"order_line_id":0,"product_code":"121013","rejected_quantity":0,"shipped_quantity":1}]},"shipped_date":"2021-06-30 09:59:00","tracking_number":"89U2038099","tracking_url":"https://auspost.com.au/mypost/track/#/details/89U2038099"},{"carrier_name":"AUSTRALIA POST","consignment_number":"consAUBW306415903_1","no_of_parcels":1,"shipment_lines":{"shipment_line":[{"order_line_id":2,"product_code":"121013","rejected_quantity":0,"shipped_quantity":1}]},"shipped_date":"2021-06-30 09:56:00","tracking_number":"89U2038080","tracking_url":"https://auspost.com.au/mypost/track/#/details/89U2038080"}]}