{"shipment":[{"carrier_name":"ALLIED O/N EXP","consignment_number":"consAUBW335414628_0","no_of_parcels":3,"shipment_lines":{"shipment_line":[{"order_line_id":0,"product_code":"131119","rejected_quantity":0,"shipped_quantity":1}]},"shipped_date":"2021-09-17 13:03:00","tracking_number":"TMV173474","tracking_url":"https://track.aftership.com/trackings?courier=alliedexpress&tracking-numbers=TMV173474&tracking_postal_code=7256"},{"carrier_name":"ALLIED O/N EXP","consignment_number":"consAUBW336244127_1","no_of_parcels":1,"shipment_lines":{"shipment_line":[{"order_line_id":3,"product_code":"81528","rejected_quantity":0,"shipped_quantity":1}]},"shipped_date":"2021-09-17 13:46:00","tracking_number":"TMV173485","tracking_url":"https://track.aftership.com/trackings?courier=alliedexpress&tracking-numbers=TMV173485&tracking_postal_code=2705"},{"carrier_name":"ALLIED O/N EXP","consignment_number":"consAUBW336437481_0","no_of_parcels":2,"shipment_lines":{"shipment_line":[{"order_line_id":0,"product_code":"81546","rejected_quantity":0,"shipped_quantity":1}]},"shipped_date":"2021-09-17 14:39:00","tracking_number":"TMV173533","tracking_url":"https://track.aftership.com/trackings?courier=alliedexpress&tracking-numbers=TMV173533&tracking_postal_code=3173"},{"carrier_name":"ALLIED O/N EXP","consignment_number":"consAUBW336472346_0","no_of_parcels":1,"shipment_lines":{"shipment_line":[{"order_line_id":0,"product_code":"81528","rejected_quantity":0,"shipped_quantity":1}]},"shipped_date":"2021-09-17 10:10:00","tracking_number":"TMV173403","tracking_url":"https://track.aftership.com/trackings?courier=alliedexpress&tracking-numbers=TMV173403&tracking_postal_code=2148"},{"carrier_name":"ALLIED O/N EXP","consignment_number":"consAUBW336485429_0","no_of_parcels":2,"shipment_lines":{"shipment_line":[{"order_line_id":8,"product_code":"121013","rejected_quantity":0,"shipped_quantity":1},{"order_line_id":7,"product_code":"81528","rejected_quantity":0,"shipped_quantity":1}]},"shipped_date":"2021-09-17 10:10:00","tracking_number":"TMV173407","tracking_url":"https://track.aftership.com/trackings?courier=alliedexpress&tracking-numbers=TMV173407&tracking_postal_code=2325"},{"carrier_name":"ALLIED O/N EXP","consignment_number":"consAUBW336567995_0","no_of_parcels":2,"shipment_lines":{"shipment_line":[{"order_line_id":0,"product_code":"81546","rejected_quantity":0,"shipped_quantity":1}]},"shipped_date":"2021-09-17 13:47:00","tracking_number":"TMV173488","tracking_url":"https://track.aftership.com/trackings?courier=alliedexpress&tracking-numbers=TMV173488&tracking_postal_code=2756"},{"carrier_name":"ALLIED O/N EXP","consignment_number":"consAUBW336571047_0","no_of_parcels":1,"shipment_lines":{"shipment_line":[{"order_line_id":0,"product_code":"81528","rejected_quantity":0,"shipped_quantity":1}]},"shipped_date":"2021-09-17 13:48:00","tracking_number":"TMV173493","tracking_url":"https://track.aftership.com/trackings?courier=alliedexpress&tracking-numbers=TMV173493&tracking_postal_code=2536"},{"carrier_name":"AUSTRALIA POST","consignment_number":"consAUBW336177361_0","no_of_parcels":1,"shipment_lines":{"shipment_line":[{"order_line_id":8,"product_code":"121013","rejected_quantity":0,"shipped_quantity":1}]},"shipped_date":"2021-09-17 10:18:00","tracking_number":"89U2046486","tracking_url":"https://auspost.com.au/mypost/track/#/details/89U2046486"},{"carrier_name":"AUSTRALIA POST","consignment_number":"consAUBW336444969_0","no_of_parcels":1,"shipment_lines":{"shipment_line":[{"order_line_id":11,"product_code":"121013","rejected_quantity":0,"shipped_quantity":1}]},"shipped_date":"2021-09-17 09:49:00","tracking_number":"89U2046460","tracking_url":"https://auspost.com.au/mypost/track/#/details/89U2046460"}]}