{"shipment":[{"carrier_name":"ALD","consignment_number":"consAUBW359188901_0","no_of_parcels":3,"shipment_lines":{"shipment_line":[{"order_line_id":0,"product_code":"225499","rejected_quantity":0,"shipped_quantity":1}]},"shipped_date":"2022-09-15 12:08:00","tracking_number":"AOE8048712A","tracking_url":"https://track.aftership.com/trackings?courier=alliedexpress&tracking-numbers=AOE8048712A&tracking_postal_code=4670"},{"carrier_name":"ALD","consignment_number":"consAUBW359220343_0","no_of_parcels":1,"shipment_lines":{"shipment_line":[{"order_line_id":0,"product_code":"81528","rejected_quantity":0,"shipped_quantity":1}]},"shipped_date":"2022-09-15 08:43:00","tracking_number":"AOE8047427K","tracking_url":"https://track.aftership.com/trackings?courier=alliedexpress&tracking-numbers=AOE8047427K&tracking_postal_code=2880"},{"carrier_name":"AUS","consignment_number":"consAUBW359186911_0","no_of_parcels":1,"shipment_lines":{"shipment_line":[{"order_line_id":0,"product_code":"121014","rejected_quantity":0,"shipped_quantity":1}]},"shipped_date":"2022-09-15 09:29:00","tracking_number":"89U5002682","tracking_url":"https://auspost.com.au/mypost/track/#/details/89U5002682"},{"carrier_name":"AUS","consignment_number":"consAUBW359188422_2","no_of_parcels":1,"shipment_lines":{"shipment_line":[{"order_line_id":0,"product_code":"121009","rejected_quantity":0,"shipped_quantity":1}]},"shipped_date":"2022-09-15 09:13:00","tracking_number":"89U5002664","tracking_url":"https://auspost.com.au/mypost/track/#/details/89U5002664"}]}