{"shipment":[{"carrier_name":"Same Day - VIC [Civic]","consignment_number":"consAUBW362962728_0","no_of_parcels":2,"shipment_lines":{"shipment_line":[{"order_line_id":0,"product_code":"187475","rejected_quantity":0,"shipped_quantity":1}]},"shipped_date":"2022-12-09 03:55:00","tracking_number":"56908","tracking_url":"https://www.civic.com.au/Home/"},{"carrier_name":"Same Day - VIC [Civic]","consignment_number":"consAUBW363284665_0","no_of_parcels":2,"shipment_lines":{"shipment_line":[{"order_line_id":0,"product_code":"187482","rejected_quantity":0,"shipped_quantity":1}]},"shipped_date":"2022-12-09 03:55:00","tracking_number":"38220","tracking_url":"https://www.civic.com.au/Home/"},{"carrier_name":"Same Day - VIC [Civic]","consignment_number":"consAUBW363298132_0","no_of_parcels":1,"shipment_lines":{"shipment_line":[{"order_line_id":0,"product_code":"225480","rejected_quantity":0,"shipped_quantity":1}]},"shipped_date":"2022-12-09 03:55:00","tracking_number":"47911","tracking_url":"https://www.civic.com.au/Home/"},{"carrier_name":"Same Day - VIC [Civic]","consignment_number":"consAUBW363613550_0","no_of_parcels":2,"shipment_lines":{"shipment_line":[{"order_line_id":0,"product_code":"187482","rejected_quantity":0,"shipped_quantity":1}]},"shipped_date":"2022-12-09 03:55:00","tracking_number":"38154","tracking_url":"https://www.civic.com.au/Home/"}]}