{"shipment":[{"carrier_name":"BLUE STAR","consignment_number":"consAUBW307100146_0","no_of_parcels":3,"shipment_lines":{"shipment_line":[{"order_line_id":0,"product_code":"81530","rejected_quantity":0,"shipped_quantity":1}]},"shipped_date":"2021-07-22 16:21:00","tracking_number":"TMSGFR12200","tracking_url":"http://www.bslots.com/2.0/Tracker.asp&tracking-numbers=TMSGFR12200&tracking_postal_code=2460"},{"carrier_name":"Same Day - VIC [Civic]","consignment_number":"consAUBW307066208_0","no_of_parcels":3,"shipment_lines":{"shipment_line":[{"order_line_id":0,"product_code":"131119","rejected_quantity":0,"shipped_quantity":1}]},"shipped_date":"2021-07-22 16:44:00","tracking_number":"87917","tracking_url":"https://www.civic.com.au/Home/"}]}