{"shipment":[{"carrier_name":"ALLIED O/N EXP","consignment_number":"consAUBW299477117_0","no_of_parcels":1,"shipment_lines":{"shipment_line":[{"order_line_id":0,"product_code":"81528","rejected_quantity":0,"shipped_quantity":1}]},"shipped_date":"2021-05-17 11:30:00","tracking_number":"TMV156839","tracking_url":"https://track.aftership.com/trackings?courier=alliedexpress&tracking-numbers=TMV156839&tracking_postal_code=4805"},{"carrier_name":"ALLIED O/N EXP","consignment_number":"consAUBW303630381_0","no_of_parcels":1,"shipment_lines":{"shipment_line":[{"order_line_id":0,"product_code":"81528","rejected_quantity":0,"shipped_quantity":1}]},"shipped_date":"2021-05-17 11:31:00","tracking_number":"TMV156843","tracking_url":"https://track.aftership.com/trackings?courier=alliedexpress&tracking-numbers=TMV156843&tracking_postal_code=4725"},{"carrier_name":"ALLIED O/N EXP","consignment_number":"consAUBW304211878_0","no_of_parcels":2,"shipment_lines":{"shipment_line":[{"order_line_id":0,"product_code":"81548","rejected_quantity":0,"shipped_quantity":1}]},"shipped_date":"2021-05-17 14:58:00","tracking_number":"TMV156929","tracking_url":"https://track.aftership.com/trackings?courier=alliedexpress&tracking-numbers=TMV156929&tracking_postal_code=2753"},{"carrier_name":"ALLIED O/N EXP","consignment_number":"consAUBW304213022_0","no_of_parcels":1,"shipment_lines":{"shipment_line":[{"order_line_id":0,"product_code":"81528","rejected_quantity":0,"shipped_quantity":1}]},"shipped_date":"2021-05-17 09:38:00","tracking_number":"TMV156813","tracking_url":"https://track.aftership.com/trackings?courier=alliedexpress&tracking-numbers=TMV156813&tracking_postal_code=0832"},{"carrier_name":"ALLIED O/N EXP","consignment_number":"consAUBW304308392_0","no_of_parcels":3,"shipment_lines":{"shipment_line":[{"order_line_id":2,"product_code":"81529","rejected_quantity":0,"shipped_quantity":1},{"order_line_id":1,"product_code":"121014","rejected_quantity":0,"shipped_quantity":1},{"order_line_id":0,"product_code":"121013","rejected_quantity":0,"shipped_quantity":1}]},"shipped_date":"2021-05-17 14:59:00","tracking_number":"TMV156930","tracking_url":"https://track.aftership.com/trackings?courier=alliedexpress&tracking-numbers=TMV156930&tracking_postal_code=2566"},{"carrier_name":"ALLIED O/N EXP","consignment_number":"consAUBW304323433_0","no_of_parcels":1,"shipment_lines":{"shipment_line":[{"order_line_id":0,"product_code":"81529","rejected_quantity":0,"shipped_quantity":1}]},"shipped_date":"2021-05-17 15:09:00","tracking_number":"TMV156971","tracking_url":"https://track.aftership.com/trackings?courier=alliedexpress&tracking-numbers=TMV156971&tracking_postal_code=2452"},{"carrier_name":"ALLIED O/N EXP","consignment_number":"consAUBW304374428_0","no_of_parcels":1,"shipment_lines":{"shipment_line":[{"order_line_id":0,"product_code":"81529","rejected_quantity":0,"shipped_quantity":1}]},"shipped_date":"2021-05-17 13:01:00","tracking_number":"TMV156895","tracking_url":"https://track.aftership.com/trackings?courier=alliedexpress&tracking-numbers=TMV156895&tracking_postal_code=3500"},{"carrier_name":"AUSTRALIA POST","consignment_number":"consAUBW304338202_1","no_of_parcels":1,"shipment_lines":{"shipment_line":[{"order_line_id":0,"product_code":"121013","rejected_quantity":0,"shipped_quantity":1}]},"shipped_date":"2021-05-17 11:15:00","tracking_number":"89U2036196","tracking_url":"https://auspost.com.au/mypost/track/#/details/89U2036196"},{"carrier_name":"AUSTRALIA POST","consignment_number":"consAUBW304372701_0","no_of_parcels":1,"shipment_lines":{"shipment_line":[{"order_line_id":0,"product_code":"121013","rejected_quantity":0,"shipped_quantity":1}]},"shipped_date":"2021-05-17 11:11:00","tracking_number":"89U2036181","tracking_url":"https://auspost.com.au/mypost/track/#/details/89U2036181"}]}