{"shipment":[{"carrier_name":"ALLIED O/N EXP","consignment_number":"consAUBW287796261_0","no_of_parcels":1,"shipment_lines":{"shipment_line":[{"order_line_id":0,"product_code":"81544","rejected_quantity":0,"shipped_quantity":1}]},"shipped_date":"2020-07-24 10:17:00","tracking_number":"TMV122841","tracking_url":"https://track.aftership.com/trackings?courier=alliedexpress&tracking-numbers=TMV122841&tracking_postal_code=3620"},{"carrier_name":"ALLIED O/N EXP","consignment_number":"consAUBW288819813_0","no_of_parcels":2,"shipment_lines":{"shipment_line":[{"order_line_id":0,"product_code":"81527","rejected_quantity":0,"shipped_quantity":1}]},"shipped_date":"2020-07-24 14:04:00","tracking_number":"TMV122955","tracking_url":"https://track.aftership.com/trackings?courier=alliedexpress&tracking-numbers=TMV122955&tracking_postal_code=6026"}]}