{"shipment":[{"carrier_name":"ALLIED O/N EXP","consignment_number":"consAUBW305012666_2","no_of_parcels":1,"shipment_lines":{"shipment_line":[{"order_line_id":0,"product_code":"81529","rejected_quantity":0,"shipped_quantity":1}]},"shipped_date":"2021-06-21 13:44:00","tracking_number":"TMV159920","tracking_url":"https://track.aftership.com/trackings?courier=alliedexpress&tracking-numbers=TMV159920&tracking_postal_code=4117"},{"carrier_name":"ALLIED O/N EXP","consignment_number":"consAUBW305212404_0","no_of_parcels":1,"shipment_lines":{"shipment_line":[{"order_line_id":0,"product_code":"81544","rejected_quantity":0,"shipped_quantity":1}]},"shipped_date":"2021-06-21 11:09:00","tracking_number":"TMV159857","tracking_url":"https://track.aftership.com/trackings?courier=alliedexpress&tracking-numbers=TMV159857&tracking_postal_code=5700"},{"carrier_name":"ALLIED O/N EXP","consignment_number":"consAUBW305337236_0","no_of_parcels":2,"shipment_lines":{"shipment_line":[{"order_line_id":0,"product_code":"81546","rejected_quantity":0,"shipped_quantity":1}]},"shipped_date":"2021-06-21 11:12:00","tracking_number":"TMV159873","tracking_url":"https://track.aftership.com/trackings?courier=alliedexpress&tracking-numbers=TMV159873&tracking_postal_code=5108"},{"carrier_name":"ALLIED O/N EXP","consignment_number":"consAUBW305548047_0","no_of_parcels":1,"shipment_lines":{"shipment_line":[{"order_line_id":0,"product_code":"81544","rejected_quantity":0,"shipped_quantity":1}]},"shipped_date":"2021-06-21 11:11:00","tracking_number":"TMV159869","tracking_url":"https://track.aftership.com/trackings?courier=alliedexpress&tracking-numbers=TMV159869&tracking_postal_code=5112"},{"carrier_name":"ALLIED O/N EXP","consignment_number":"consAUBW305554032_0","no_of_parcels":4,"shipment_lines":{"shipment_line":[{"order_line_id":0,"product_code":"166799","rejected_quantity":0,"shipped_quantity":1}]},"shipped_date":"2021-06-21 09:59:00","tracking_number":"TMV159846","tracking_url":"https://track.aftership.com/trackings?courier=alliedexpress&tracking-numbers=TMV159846&tracking_postal_code=6027"},{"carrier_name":"ALLIED O/N EXP","consignment_number":"consAUBW305653882_0","no_of_parcels":1,"shipment_lines":{"shipment_line":[{"order_line_id":0,"product_code":"81529","rejected_quantity":0,"shipped_quantity":1}]},"shipped_date":"2021-06-21 09:59:00","tracking_number":"TMV159848","tracking_url":"https://track.aftership.com/trackings?courier=alliedexpress&tracking-numbers=TMV159848&tracking_postal_code=6024"},{"carrier_name":"ALLIED O/N EXP","consignment_number":"consAUBW305707109_0","no_of_parcels":1,"shipment_lines":{"shipment_line":[{"order_line_id":0,"product_code":"81544","rejected_quantity":0,"shipped_quantity":1}]},"shipped_date":"2021-06-21 11:58:00","tracking_number":"TMV159884","tracking_url":"https://track.aftership.com/trackings?courier=alliedexpress&tracking-numbers=TMV159884&tracking_postal_code=4132"},{"carrier_name":"ALLIED O/N EXP","consignment_number":"consAUBW305763061_0","no_of_parcels":1,"shipment_lines":{"shipment_line":[{"order_line_id":0,"product_code":"81529","rejected_quantity":0,"shipped_quantity":1}]},"shipped_date":"2021-06-21 13:46:00","tracking_number":"TMV159932","tracking_url":"https://track.aftership.com/trackings?courier=alliedexpress&tracking-numbers=TMV159932&tracking_postal_code=4124"},{"carrier_name":"ALLIED O/N EXP","consignment_number":"consAUBW305830624_0","no_of_parcels":1,"shipment_lines":{"shipment_line":[{"order_line_id":0,"product_code":"81529","rejected_quantity":0,"shipped_quantity":1}]},"shipped_date":"2021-06-21 11:11:00","tracking_number":"TMV159871","tracking_url":"https://track.aftership.com/trackings?courier=alliedexpress&tracking-numbers=TMV159871&tracking_postal_code=5075"},{"carrier_name":"ALLIED O/N EXP","consignment_number":"consAUBW305834700_0","no_of_parcels":6,"shipment_lines":{"shipment_line":[{"order_line_id":0,"product_code":"166798","rejected_quantity":0,"shipped_quantity":1}]},"shipped_date":"2021-06-21 15:10:00","tracking_number":"TMV159965","tracking_url":"https://track.aftership.com/trackings?courier=alliedexpress&tracking-numbers=TMV159965&tracking_postal_code=2440"},{"carrier_name":"ALLIED O/N EXP","consignment_number":"consAUBW305845290_0","no_of_parcels":6,"shipment_lines":{"shipment_line":[{"order_line_id":0,"product_code":"166798","rejected_quantity":0,"shipped_quantity":1}]},"shipped_date":"2021-06-21 13:47:00","tracking_number":"TMV159934","tracking_url":"https://track.aftership.com/trackings?courier=alliedexpress&tracking-numbers=TMV159934&tracking_postal_code=4570"},{"carrier_name":"ALLIED O/N EXP","consignment_number":"consAUBW305846539_0","no_of_parcels":2,"shipment_lines":{"shipment_line":[{"order_line_id":0,"product_code":"81546","rejected_quantity":0,"shipped_quantity":1}]},"shipped_date":"2021-06-21 09:57:00","tracking_number":"TMV159839","tracking_url":"https://track.aftership.com/trackings?courier=alliedexpress&tracking-numbers=TMV159839&tracking_postal_code=6180"},{"carrier_name":"ALLIED O/N EXP","consignment_number":"consAUBW305849076_0","no_of_parcels":2,"shipment_lines":{"shipment_line":[{"order_line_id":0,"product_code":"81546","rejected_quantity":0,"shipped_quantity":1}]},"shipped_date":"2021-06-21 15:09:00","tracking_number":"TMV159961","tracking_url":"https://track.aftership.com/trackings?courier=alliedexpress&tracking-numbers=TMV159961&tracking_postal_code=2760"},{"carrier_name":"ALLIED O/N EXP","consignment_number":"consAUBW305859431_0","no_of_parcels":1,"shipment_lines":{"shipment_line":[{"order_line_id":0,"product_code":"81544","rejected_quantity":0,"shipped_quantity":1}]},"shipped_date":"2021-06-21 15:07:00","tracking_number":"TMV159946","tracking_url":"https://track.aftership.com/trackings?courier=alliedexpress&tracking-numbers=TMV159946&tracking_postal_code=2830"},{"carrier_name":"ALLIED O/N EXP","consignment_number":"consAUBW305863685_0","no_of_parcels":2,"shipment_lines":{"shipment_line":[{"order_line_id":0,"product_code":"81546","rejected_quantity":0,"shipped_quantity":1}]},"shipped_date":"2021-06-21 15:10:00","tracking_number":"TMV159966","tracking_url":"https://track.aftership.com/trackings?courier=alliedexpress&tracking-numbers=TMV159966&tracking_postal_code=2234"},{"carrier_name":"ALLIED O/N EXP","consignment_number":"consAUBW305880059_0","no_of_parcels":1,"shipment_lines":{"shipment_line":[{"order_line_id":0,"product_code":"81544","rejected_quantity":0,"shipped_quantity":1}]},"shipped_date":"2021-06-21 13:43:00","tracking_number":"TMV159916","tracking_url":"https://track.aftership.com/trackings?courier=alliedexpress&tracking-numbers=TMV159916&tracking_postal_code=4621"},{"carrier_name":"ALLIED O/N EXP","consignment_number":"consAUBW305880149_0","no_of_parcels":1,"shipment_lines":{"shipment_line":[{"order_line_id":0,"product_code":"81544","rejected_quantity":0,"shipped_quantity":1}]},"shipped_date":"2021-06-21 15:31:00","tracking_number":"TMV159981","tracking_url":"https://track.aftership.com/trackings?courier=alliedexpress&tracking-numbers=TMV159981&tracking_postal_code=2880"},{"carrier_name":"ALLIED O/N EXP","consignment_number":"consAUBW305880843_0","no_of_parcels":1,"shipment_lines":{"shipment_line":[{"order_line_id":0,"product_code":"81544","rejected_quantity":0,"shipped_quantity":1}]},"shipped_date":"2021-06-21 13:43:00","tracking_number":"TMV159917","tracking_url":"https://track.aftership.com/trackings?courier=alliedexpress&tracking-numbers=TMV159917&tracking_postal_code=4670"},{"carrier_name":"ALLIED O/N EXP","consignment_number":"consAUBW305905972_0","no_of_parcels":1,"shipment_lines":{"shipment_line":[{"order_line_id":0,"product_code":"81529","rejected_quantity":0,"shipped_quantity":1}]},"shipped_date":"2021-06-21 13:47:00","tracking_number":"TMV159939","tracking_url":"https://track.aftership.com/trackings?courier=alliedexpress&tracking-numbers=TMV159939&tracking_postal_code=4209"},{"carrier_name":"ALLIED O/N EXP","consignment_number":"consAUBW305907373_0","no_of_parcels":1,"shipment_lines":{"shipment_line":[{"order_line_id":0,"product_code":"81544","rejected_quantity":0,"shipped_quantity":1}]},"shipped_date":"2021-06-21 11:11:00","tracking_number":"TMV159868","tracking_url":"https://track.aftership.com/trackings?courier=alliedexpress&tracking-numbers=TMV159868&tracking_postal_code=5162"},{"carrier_name":"ALLIED O/N EXP","consignment_number":"consAUBW305916776_2","no_of_parcels":1,"shipment_lines":{"shipment_line":[{"order_line_id":0,"product_code":"81529","rejected_quantity":0,"shipped_quantity":1}]},"shipped_date":"2021-06-21 11:10:00","tracking_number":"TMV159865","tracking_url":"https://track.aftership.com/trackings?courier=alliedexpress&tracking-numbers=TMV159865&tracking_postal_code=5710"},{"carrier_name":"ALLIED O/N EXP","consignment_number":"consAUBW305950823_0","no_of_parcels":1,"shipment_lines":{"shipment_line":[{"order_line_id":0,"product_code":"81544","rejected_quantity":0,"shipped_quantity":1}]},"shipped_date":"2021-06-21 11:57:00","tracking_number":"TMV159875","tracking_url":"https://track.aftership.com/trackings?courier=alliedexpress&tracking-numbers=TMV159875&tracking_postal_code=4285"},{"carrier_name":"ALLIED O/N EXP","consignment_number":"consAUBW305958201_0","no_of_parcels":1,"shipment_lines":{"shipment_line":[{"order_line_id":0,"product_code":"81529","rejected_quantity":0,"shipped_quantity":1}]},"shipped_date":"2021-06-21 12:02:00","tracking_number":"TMV159904","tracking_url":"https://track.aftership.com/trackings?courier=alliedexpress&tracking-numbers=TMV159904&tracking_postal_code=4209"},{"carrier_name":"ALLIED O/N EXP","consignment_number":"consAUBW305962582_0","no_of_parcels":1,"shipment_lines":{"shipment_line":[{"order_line_id":0,"product_code":"81529","rejected_quantity":0,"shipped_quantity":1}]},"shipped_date":"2021-06-21 11:09:00","tracking_number":"TMV159856","tracking_url":"https://track.aftership.com/trackings?courier=alliedexpress&tracking-numbers=TMV159856&tracking_postal_code=5260"},{"carrier_name":"ALLIED O/N EXP","consignment_number":"consAUBW305967770_0","no_of_parcels":1,"shipment_lines":{"shipment_line":[{"order_line_id":0,"product_code":"81529","rejected_quantity":0,"shipped_quantity":1}]},"shipped_date":"2021-06-21 12:02:00","tracking_number":"TMV159905","tracking_url":"https://track.aftership.com/trackings?courier=alliedexpress&tracking-numbers=TMV159905&tracking_postal_code=4132"},{"carrier_name":"ALLIED O/N EXP","consignment_number":"consAUBW305977268_0","no_of_parcels":1,"shipment_lines":{"shipment_line":[{"order_line_id":0,"product_code":"81529","rejected_quantity":0,"shipped_quantity":1}]},"shipped_date":"2021-06-21 12:00:00","tracking_number":"TMV159892","tracking_url":"https://track.aftership.com/trackings?courier=alliedexpress&tracking-numbers=TMV159892&tracking_postal_code=4507"},{"carrier_name":"ALLIED O/N EXP","consignment_number":"consAUBW305982790_0","no_of_parcels":1,"shipment_lines":{"shipment_line":[{"order_line_id":0,"product_code":"81544","rejected_quantity":0,"shipped_quantity":1}]},"shipped_date":"2021-06-21 15:32:00","tracking_number":"TMV159990","tracking_url":"https://track.aftership.com/trackings?courier=alliedexpress&tracking-numbers=TMV159990&tracking_postal_code=2153"},{"carrier_name":"ALLIED O/N EXP","consignment_number":"consAUBW305992691_0","no_of_parcels":1,"shipment_lines":{"shipment_line":[{"order_line_id":0,"product_code":"81544","rejected_quantity":0,"shipped_quantity":1}]},"shipped_date":"2021-06-21 15:31:00","tracking_number":"TMV159982","tracking_url":"https://track.aftership.com/trackings?courier=alliedexpress&tracking-numbers=TMV159982&tracking_postal_code=2191"},{"carrier_name":"ALLIED O/N EXP","consignment_number":"consAUBW305994544_0","no_of_parcels":1,"shipment_lines":{"shipment_line":[{"order_line_id":0,"product_code":"81529","rejected_quantity":0,"shipped_quantity":1}]},"shipped_date":"2021-06-21 12:00:00","tracking_number":"TMV159895","tracking_url":"https://track.aftership.com/trackings?courier=alliedexpress&tracking-numbers=TMV159895&tracking_postal_code=4154"},{"carrier_name":"AUSTRALIA POST","consignment_number":"consAUBW305773112_1","no_of_parcels":1,"shipment_lines":{"shipment_line":[{"order_line_id":8,"product_code":"121014","rejected_quantity":0,"shipped_quantity":1}]},"shipped_date":"2021-06-21 11:45:00","tracking_number":"89U2037614","tracking_url":"https://auspost.com.au/mypost/track/#/details/89U2037614"},{"carrier_name":"AUSTRALIA POST","consignment_number":"consAUBW305821904_0","no_of_parcels":1,"shipment_lines":{"shipment_line":[{"order_line_id":0,"product_code":"121014","rejected_quantity":0,"shipped_quantity":1}]},"shipped_date":"2021-06-21 14:31:00","tracking_number":"89U2037642","tracking_url":"https://auspost.com.au/mypost/track/#/details/89U2037642"},{"carrier_name":"AUSTRALIA POST","consignment_number":"consAUBW305849963_0","no_of_parcels":1,"shipment_lines":{"shipment_line":[{"order_line_id":0,"product_code":"121013","rejected_quantity":0,"shipped_quantity":1}]},"shipped_date":"2021-06-21 11:40:00","tracking_number":"89U2037585","tracking_url":"https://auspost.com.au/mypost/track/#/details/89U2037585"},{"carrier_name":"AUSTRALIA POST","consignment_number":"consAUBW305850180_0","no_of_parcels":1,"shipment_lines":{"shipment_line":[{"order_line_id":0,"product_code":"121013","rejected_quantity":0,"shipped_quantity":1}]},"shipped_date":"2021-06-21 11:47:00","tracking_number":"89U2037626","tracking_url":"https://auspost.com.au/mypost/track/#/details/89U2037626"},{"carrier_name":"AUSTRALIA POST","consignment_number":"consAUBW305894027_1","no_of_parcels":1,"shipment_lines":{"shipment_line":[{"order_line_id":0,"product_code":"121014","rejected_quantity":0,"shipped_quantity":1}]},"shipped_date":"2021-06-21 11:46:00","tracking_number":"89U2037619","tracking_url":"https://auspost.com.au/mypost/track/#/details/89U2037619"},{"carrier_name":"AUSTRALIA POST","consignment_number":"consAUBW305898264_0","no_of_parcels":1,"shipment_lines":{"shipment_line":[{"order_line_id":0,"product_code":"121014","rejected_quantity":0,"shipped_quantity":1}]},"shipped_date":"2021-06-21 11:45:00","tracking_number":"89U2037615","tracking_url":"https://auspost.com.au/mypost/track/#/details/89U2037615"},{"carrier_name":"AUSTRALIA POST","consignment_number":"consAUBW305910835_0","no_of_parcels":1,"shipment_lines":{"shipment_line":[{"order_line_id":0,"product_code":"121009","rejected_quantity":0,"shipped_quantity":1}]},"shipped_date":"2021-06-21 11:46:00","tracking_number":"89U2037617","tracking_url":"https://auspost.com.au/mypost/track/#/details/89U2037617"},{"carrier_name":"AUSTRALIA POST","consignment_number":"consAUBW305911084_0","no_of_parcels":1,"shipment_lines":{"shipment_line":[{"order_line_id":0,"product_code":"121013","rejected_quantity":0,"shipped_quantity":1}]},"shipped_date":"2021-06-21 11:46:00","tracking_number":"89U2037616","tracking_url":"https://auspost.com.au/mypost/track/#/details/89U2037616"},{"carrier_name":"AUSTRALIA POST","consignment_number":"consAUBW305916877_1","no_of_parcels":1,"shipment_lines":{"shipment_line":[{"order_line_id":10,"product_code":"121014","rejected_quantity":0,"shipped_quantity":1}]},"shipped_date":"2021-06-21 11:41:00","tracking_number":"89U2037589","tracking_url":"https://auspost.com.au/mypost/track/#/details/89U2037589"},{"carrier_name":"AUSTRALIA POST","consignment_number":"consAUBW305917980_1","no_of_parcels":1,"shipment_lines":{"shipment_line":[{"order_line_id":3,"product_code":"121014","rejected_quantity":0,"shipped_quantity":1}]},"shipped_date":"2021-06-21 11:43:00","tracking_number":"89U2037598","tracking_url":"https://auspost.com.au/mypost/track/#/details/89U2037598"},{"carrier_name":"AUSTRALIA POST","consignment_number":"consAUBW305920450_0","no_of_parcels":1,"shipment_lines":{"shipment_line":[{"order_line_id":1,"product_code":"121014","rejected_quantity":0,"shipped_quantity":1}]},"shipped_date":"2021-06-21 14:30:00","tracking_number":"89U2037635","tracking_url":"https://auspost.com.au/mypost/track/#/details/89U2037635"},{"carrier_name":"AUSTRALIA POST","consignment_number":"consAUBW305946870_0","no_of_parcels":1,"shipment_lines":{"shipment_line":[{"order_line_id":0,"product_code":"121009","rejected_quantity":0,"shipped_quantity":1}]},"shipped_date":"2021-06-21 14:32:00","tracking_number":"89U2037650","tracking_url":"https://auspost.com.au/mypost/track/#/details/89U2037650"},{"carrier_name":"AUSTRALIA POST","consignment_number":"consAUBW305960430_0","no_of_parcels":1,"shipment_lines":{"shipment_line":[{"order_line_id":0,"product_code":"121013","rejected_quantity":0,"shipped_quantity":1}]},"shipped_date":"2021-06-21 11:44:00","tracking_number":"89U2037605","tracking_url":"https://auspost.com.au/mypost/track/#/details/89U2037605"},{"carrier_name":"AUSTRALIA POST","consignment_number":"consAUBW305961025_0","no_of_parcels":1,"shipment_lines":{"shipment_line":[{"order_line_id":0,"product_code":"121013","rejected_quantity":0,"shipped_quantity":1}]},"shipped_date":"2021-06-21 14:32:00","tracking_number":"89U2037649","tracking_url":"https://auspost.com.au/mypost/track/#/details/89U2037649"},{"carrier_name":"AUSTRALIA POST","consignment_number":"consAUBW305989711_0","no_of_parcels":1,"shipment_lines":{"shipment_line":[{"order_line_id":0,"product_code":"121014","rejected_quantity":0,"shipped_quantity":1}]},"shipped_date":"2021-06-21 11:46:00","tracking_number":"89U2037620","tracking_url":"https://auspost.com.au/mypost/track/#/details/89U2037620"},{"carrier_name":"AUSTRALIA POST","consignment_number":"consAUBW305996344_0","no_of_parcels":1,"shipment_lines":{"shipment_line":[{"order_line_id":0,"product_code":"121007","rejected_quantity":0,"shipped_quantity":1}]},"shipped_date":"2021-06-21 11:47:00","tracking_number":"89U2037623","tracking_url":"https://auspost.com.au/mypost/track/#/details/89U2037623"},{"carrier_name":"AUSTRALIA POST","consignment_number":"consAUBW306002564_0","no_of_parcels":1,"shipment_lines":{"shipment_line":[{"order_line_id":8,"product_code":"121014","rejected_quantity":0,"shipped_quantity":1}]},"shipped_date":"2021-06-21 11:47:00","tracking_number":"89U2037625","tracking_url":"https://auspost.com.au/mypost/track/#/details/89U2037625"},{"carrier_name":"DIRECT FRT","consignment_number":"consAUBW305494241_0","no_of_parcels":1,"shipment_lines":{"shipment_line":[{"order_line_id":1,"product_code":"119930","rejected_quantity":0,"shipped_quantity":1}]},"shipped_date":"2021-06-21 14:21:00","tracking_number":"3455801000714","tracking_url":"http://www.smartfreight.com/tracking&tracking-numbers=3455801000714&tracking_postal_code=2570"}]}