{"shipment":[{"carrier_name":"ALD","consignment_number":"consAUBW372517743_0","no_of_parcels":2,"shipment_lines":{"shipment_line":[{"order_line_id":0,"product_code":"187475","rejected_quantity":0,"shipped_quantity":1}]},"shipped_date":"2023-06-30 14:17:00","tracking_number":"GFB006357","tracking_url":"https://track.aftership.com/trackings?courier=alliedexpress&tracking-numbers=GFB006357&tracking_postal_code=2320"},{"carrier_name":"ALD","consignment_number":"consAUBW372839916_0","no_of_parcels":2,"shipment_lines":{"shipment_line":[{"order_line_id":0,"product_code":"187477","rejected_quantity":0,"shipped_quantity":1}]},"shipped_date":"2023-06-30 10:14:00","tracking_number":"GFB006300","tracking_url":"https://track.aftership.com/trackings?courier=alliedexpress&tracking-numbers=GFB006300&tracking_postal_code=3930"},{"carrier_name":"ALD","consignment_number":"consAUBW372937360_0","no_of_parcels":1,"shipment_lines":{"shipment_line":[{"order_line_id":0,"product_code":"296891","rejected_quantity":0,"shipped_quantity":1}]},"shipped_date":"2023-06-30 10:15:00","tracking_number":"GFB006304","tracking_url":"https://track.aftership.com/trackings?courier=alliedexpress&tracking-numbers=GFB006304&tracking_postal_code=3019"},{"carrier_name":"ALD","consignment_number":"consAUBW372939012_0","no_of_parcels":3,"shipment_lines":{"shipment_line":[{"order_line_id":0,"product_code":"81530","rejected_quantity":0,"shipped_quantity":1}]},"shipped_date":"2023-06-30 14:18:00","tracking_number":"GFB006363","tracking_url":"https://track.aftership.com/trackings?courier=alliedexpress&tracking-numbers=GFB006363&tracking_postal_code=2285"},{"carrier_name":"ALD","consignment_number":"consAUBW372943581_0","no_of_parcels":2,"shipment_lines":{"shipment_line":[{"order_line_id":0,"product_code":"187482","rejected_quantity":0,"shipped_quantity":1}]},"shipped_date":"2023-06-30 10:14:00","tracking_number":"GFB006298","tracking_url":"https://track.aftership.com/trackings?courier=alliedexpress&tracking-numbers=GFB006298&tracking_postal_code=3690"},{"carrier_name":"ALD","consignment_number":"consAUBW372950630_0","no_of_parcels":2,"shipment_lines":{"shipment_line":[{"order_line_id":0,"product_code":"225536","rejected_quantity":0,"shipped_quantity":1}]},"shipped_date":"2023-06-30 09:28:00","tracking_number":"GFB006294","tracking_url":"https://track.aftership.com/trackings?courier=alliedexpress&tracking-numbers=GFB006294&tracking_postal_code=5127"},{"carrier_name":"ALD","consignment_number":"consAUBW372959746_0","no_of_parcels":3,"shipment_lines":{"shipment_line":[{"order_line_id":0,"product_code":"81530","rejected_quantity":0,"shipped_quantity":1}]},"shipped_date":"2023-06-30 14:15:00","tracking_number":"GFB006350","tracking_url":"https://track.aftership.com/trackings?courier=alliedexpress&tracking-numbers=GFB006350&tracking_postal_code=2257"},{"carrier_name":"ALD","consignment_number":"consAUBW372964684_0","no_of_parcels":1,"shipment_lines":{"shipment_line":[{"order_line_id":0,"product_code":"296891","rejected_quantity":0,"shipped_quantity":1}]},"shipped_date":"2023-06-30 12:24:00","tracking_number":"GFB006322","tracking_url":"https://track.aftership.com/trackings?courier=alliedexpress&tracking-numbers=GFB006322&tracking_postal_code=4012"},{"carrier_name":"DFE","consignment_number":"consAUBW372954910_0","no_of_parcels":1,"shipment_lines":{"shipment_line":[{"order_line_id":0,"product_code":"225502","rejected_quantity":0,"shipped_quantity":1}]},"shipped_date":"2023-06-30 10:49:00","tracking_number":"3455810009136","tracking_url":"http://www.smartfreight.com/tracking&tracking-numbers=3455810009136&tracking_postal_code=5050"},{"carrier_name":"DFE","consignment_number":"consAUBW372969033_0","no_of_parcels":1,"shipment_lines":{"shipment_line":[{"order_line_id":0,"product_code":"225502","rejected_quantity":0,"shipped_quantity":1}]},"shipped_date":"2023-06-30 10:49:00","tracking_number":"3455810009133","tracking_url":"http://www.smartfreight.com/tracking&tracking-numbers=3455810009133&tracking_postal_code=4055"}]}