{"shipment":[{"carrier_name":"ALLIED O/N EXP","consignment_number":"consAUBW307074227_0","no_of_parcels":2,"shipment_lines":{"shipment_line":[{"order_line_id":0,"product_code":"81546","rejected_quantity":0,"shipped_quantity":1}]},"shipped_date":"2021-08-30 12:08:00","tracking_number":"TMV168538","tracking_url":"https://track.aftership.com/trackings?courier=alliedexpress&tracking-numbers=TMV168538&tracking_postal_code=2321"},{"carrier_name":"ALLIED O/N EXP","consignment_number":"consAUBW332675326_0","no_of_parcels":2,"shipment_lines":{"shipment_line":[{"order_line_id":0,"product_code":"81546","rejected_quantity":0,"shipped_quantity":1}]},"shipped_date":"2021-08-30 11:33:00","tracking_number":"TMV168532","tracking_url":"https://track.aftership.com/trackings?courier=alliedexpress&tracking-numbers=TMV168532&tracking_postal_code=2560"},{"carrier_name":"ALLIED O/N EXP","consignment_number":"consAUBW333291363_0","no_of_parcels":2,"shipment_lines":{"shipment_line":[{"order_line_id":0,"product_code":"81546","rejected_quantity":0,"shipped_quantity":1}]},"shipped_date":"2021-08-30 11:33:00","tracking_number":"TMV168533","tracking_url":"https://track.aftership.com/trackings?courier=alliedexpress&tracking-numbers=TMV168533&tracking_postal_code=2334"},{"carrier_name":"ALLIED O/N EXP","consignment_number":"consAUBW333371364_0","no_of_parcels":2,"shipment_lines":{"shipment_line":[{"order_line_id":0,"product_code":"81546","rejected_quantity":0,"shipped_quantity":1}]},"shipped_date":"2021-08-30 11:32:00","tracking_number":"TMV168525","tracking_url":"https://track.aftership.com/trackings?courier=alliedexpress&tracking-numbers=TMV168525&tracking_postal_code=2517"},{"carrier_name":"ALLIED O/N EXP","consignment_number":"consAUBW333377302_0","no_of_parcels":2,"shipment_lines":{"shipment_line":[{"order_line_id":0,"product_code":"81546","rejected_quantity":0,"shipped_quantity":1}]},"shipped_date":"2021-08-30 11:31:00","tracking_number":"TMV168523","tracking_url":"https://track.aftership.com/trackings?courier=alliedexpress&tracking-numbers=TMV168523&tracking_postal_code=2525"},{"carrier_name":"ALLIED O/N EXP","consignment_number":"consAUBW333524532_0","no_of_parcels":2,"shipment_lines":{"shipment_line":[{"order_line_id":0,"product_code":"81546","rejected_quantity":0,"shipped_quantity":1}]},"shipped_date":"2021-08-30 11:31:00","tracking_number":"TMV168522","tracking_url":"https://track.aftership.com/trackings?courier=alliedexpress&tracking-numbers=TMV168522&tracking_postal_code=2780"},{"carrier_name":"ALLIED O/N EXP","consignment_number":"consAUBW333696708_0","no_of_parcels":2,"shipment_lines":{"shipment_line":[{"order_line_id":0,"product_code":"81546","rejected_quantity":0,"shipped_quantity":1}]},"shipped_date":"2021-08-30 11:33:00","tracking_number":"TMV168534","tracking_url":"https://track.aftership.com/trackings?courier=alliedexpress&tracking-numbers=TMV168534&tracking_postal_code=2321"},{"carrier_name":"ALLIED O/N EXP","consignment_number":"consAUBW333761247_0","no_of_parcels":2,"shipment_lines":{"shipment_line":[{"order_line_id":0,"product_code":"81546","rejected_quantity":0,"shipped_quantity":1}]},"shipped_date":"2021-08-30 12:09:00","tracking_number":"TMV168542","tracking_url":"https://track.aftership.com/trackings?courier=alliedexpress&tracking-numbers=TMV168542&tracking_postal_code=2179"},{"carrier_name":"ALLIED O/N EXP","consignment_number":"consAUBW333783041_0","no_of_parcels":2,"shipment_lines":{"shipment_line":[{"order_line_id":0,"product_code":"81546","rejected_quantity":0,"shipped_quantity":1}]},"shipped_date":"2021-08-30 12:10:00","tracking_number":"TMV168547","tracking_url":"https://track.aftership.com/trackings?courier=alliedexpress&tracking-numbers=TMV168547&tracking_postal_code=2577"},{"carrier_name":"ALLIED O/N EXP","consignment_number":"consAUBW333788630_0","no_of_parcels":2,"shipment_lines":{"shipment_line":[{"order_line_id":0,"product_code":"81546","rejected_quantity":0,"shipped_quantity":1}]},"shipped_date":"2021-08-30 12:09:00","tracking_number":"TMV168540","tracking_url":"https://track.aftership.com/trackings?courier=alliedexpress&tracking-numbers=TMV168540&tracking_postal_code=2630"},{"carrier_name":"ALLIED O/N EXP","consignment_number":"consAUBW333814095_0","no_of_parcels":2,"shipment_lines":{"shipment_line":[{"order_line_id":0,"product_code":"81546","rejected_quantity":0,"shipped_quantity":1}]},"shipped_date":"2021-08-30 12:10:00","tracking_number":"TMV168544","tracking_url":"https://track.aftership.com/trackings?courier=alliedexpress&tracking-numbers=TMV168544&tracking_postal_code=2155"},{"carrier_name":"ALLIED O/N EXP","consignment_number":"consAUBW333841002_0","no_of_parcels":2,"shipment_lines":{"shipment_line":[{"order_line_id":0,"product_code":"81546","rejected_quantity":0,"shipped_quantity":1}]},"shipped_date":"2021-08-30 12:10:00","tracking_number":"TMV168545","tracking_url":"https://track.aftership.com/trackings?courier=alliedexpress&tracking-numbers=TMV168545&tracking_postal_code=2528"},{"carrier_name":"ALLIED O/N EXP","consignment_number":"consAUBW333884865_0","no_of_parcels":2,"shipment_lines":{"shipment_line":[{"order_line_id":0,"product_code":"81546","rejected_quantity":0,"shipped_quantity":1}]},"shipped_date":"2021-08-30 12:09:00","tracking_number":"TMV168543","tracking_url":"https://track.aftership.com/trackings?courier=alliedexpress&tracking-numbers=TMV168543&tracking_postal_code=2041"},{"carrier_name":"ALLIED O/N EXP","consignment_number":"consAUBW333976607_0","no_of_parcels":2,"shipment_lines":{"shipment_line":[{"order_line_id":0,"product_code":"81546","rejected_quantity":0,"shipped_quantity":1}]},"shipped_date":"2021-08-30 12:10:00","tracking_number":"TMV168546","tracking_url":"https://track.aftership.com/trackings?courier=alliedexpress&tracking-numbers=TMV168546&tracking_postal_code=2770"},{"carrier_name":"ALLIED O/N EXP","consignment_number":"consAUBW333977893_0","no_of_parcels":2,"shipment_lines":{"shipment_line":[{"order_line_id":0,"product_code":"81546","rejected_quantity":0,"shipped_quantity":1}]},"shipped_date":"2021-08-30 12:08:00","tracking_number":"TMV168537","tracking_url":"https://track.aftership.com/trackings?courier=alliedexpress&tracking-numbers=TMV168537&tracking_postal_code=2750"},{"carrier_name":"ALLIED O/N EXP","consignment_number":"consAUBW334051887_0","no_of_parcels":2,"shipment_lines":{"shipment_line":[{"order_line_id":0,"product_code":"81546","rejected_quantity":0,"shipped_quantity":1}]},"shipped_date":"2021-08-30 12:08:00","tracking_number":"TMV168539","tracking_url":"https://track.aftership.com/trackings?courier=alliedexpress&tracking-numbers=TMV168539&tracking_postal_code=2835"},{"carrier_name":"ALLIED O/N EXP","consignment_number":"consAUBW334336749_0","no_of_parcels":2,"shipment_lines":{"shipment_line":[{"order_line_id":0,"product_code":"81546","rejected_quantity":0,"shipped_quantity":1}]},"shipped_date":"2021-08-30 12:10:00","tracking_number":"TMV168548","tracking_url":"https://track.aftership.com/trackings?courier=alliedexpress&tracking-numbers=TMV168548&tracking_postal_code=2759"},{"carrier_name":"AUSTRALIA POST","consignment_number":"consAUBW333590240_0","no_of_parcels":2,"shipment_lines":{"shipment_line":[{"order_line_id":1,"product_code":"121014","rejected_quantity":0,"shipped_quantity":2}]},"shipped_date":"2021-08-30 09:27:00","tracking_number":"89U2042920","tracking_url":"https://auspost.com.au/mypost/track/#/details/89U2042920"},{"carrier_name":"BLUE STAR","consignment_number":"consAUBW333662433_0","no_of_parcels":5,"shipment_lines":{"shipment_line":[{"order_line_id":0,"product_code":"131121","rejected_quantity":0,"shipped_quantity":1}]},"shipped_date":"2021-08-30 14:35:00","tracking_number":"TMSGFR14640","tracking_url":"http://www.bslots.com/2.0/Tracker.asp&tracking-numbers=TMSGFR14640&tracking_postal_code=3429"},{"carrier_name":"BLUE STAR","consignment_number":"consAUBW334039382_0","no_of_parcels":1,"shipment_lines":{"shipment_line":[{"order_line_id":0,"product_code":"81542","rejected_quantity":0,"shipped_quantity":1}]},"shipped_date":"2021-08-30 12:32:00","tracking_number":"TMSGFR14583","tracking_url":"http://www.bslots.com/2.0/Tracker.asp&tracking-numbers=TMSGFR14583&tracking_postal_code=2753"},{"carrier_name":"BLUE STAR","consignment_number":"consAUBW334418191_0","no_of_parcels":2,"shipment_lines":{"shipment_line":[{"order_line_id":0,"product_code":"81546","rejected_quantity":0,"shipped_quantity":1}]},"shipped_date":"2021-08-30 12:34:00","tracking_number":"TMSGFR14590","tracking_url":"http://www.bslots.com/2.0/Tracker.asp&tracking-numbers=TMSGFR14590&tracking_postal_code=2646"},{"carrier_name":"BLUE STAR","consignment_number":"consAUBW334586292_0","no_of_parcels":2,"shipment_lines":{"shipment_line":[{"order_line_id":0,"product_code":"81546","rejected_quantity":0,"shipped_quantity":1}]},"shipped_date":"2021-08-30 12:34:00","tracking_number":"TMSGFR14591","tracking_url":"http://www.bslots.com/2.0/Tracker.asp&tracking-numbers=TMSGFR14591&tracking_postal_code=2575"},{"carrier_name":"BLUE STAR","consignment_number":"consAUBW334624240_0","no_of_parcels":2,"shipment_lines":{"shipment_line":[{"order_line_id":0,"product_code":"81546","rejected_quantity":0,"shipped_quantity":1}]},"shipped_date":"2021-08-30 12:33:00","tracking_number":"TMSGFR14585","tracking_url":"http://www.bslots.com/2.0/Tracker.asp&tracking-numbers=TMSGFR14585&tracking_postal_code=2284"},{"carrier_name":"BLUE STAR","consignment_number":"consAUBW334631341_0","no_of_parcels":2,"shipment_lines":{"shipment_line":[{"order_line_id":0,"product_code":"81546","rejected_quantity":0,"shipped_quantity":1}]},"shipped_date":"2021-08-30 12:34:00","tracking_number":"TMSGFR14589","tracking_url":"http://www.bslots.com/2.0/Tracker.asp&tracking-numbers=TMSGFR14589&tracking_postal_code=2529"}]}