{"shipment":[{"carrier_name":"ALD","consignment_number":"consAUBW359760972_0","no_of_parcels":2,"shipment_lines":{"shipment_line":[{"order_line_id":0,"product_code":"225534","rejected_quantity":0,"shipped_quantity":1}]},"shipped_date":"2022-11-15 12:35:00","tracking_number":"AOE8274033D","tracking_url":"https://track.aftership.com/trackings?courier=alliedexpress&tracking-numbers=AOE8274033D&tracking_postal_code=4305"},{"carrier_name":"ALD","consignment_number":"consAUBW361857347_0","no_of_parcels":2,"shipment_lines":{"shipment_line":[{"order_line_id":0,"product_code":"225512","rejected_quantity":0,"shipped_quantity":1}]},"shipped_date":"2022-11-15 09:34:00","tracking_number":"AOE8272244G","tracking_url":"https://track.aftership.com/trackings?courier=alliedexpress&tracking-numbers=AOE8272244G&tracking_postal_code=2444"},{"carrier_name":"ALD","consignment_number":"consAUBW361903014_1","no_of_parcels":2,"shipment_lines":{"shipment_line":[{"order_line_id":4,"product_code":"187482","rejected_quantity":0,"shipped_quantity":1}]},"shipped_date":"2022-11-15 12:39:00","tracking_number":"AOE8274080Y","tracking_url":"https://track.aftership.com/trackings?courier=alliedexpress&tracking-numbers=AOE8274080Y&tracking_postal_code=4060"},{"carrier_name":"ALD","consignment_number":"consAUBW361948461_0","no_of_parcels":1,"shipment_lines":{"shipment_line":[{"order_line_id":1,"product_code":"81542","rejected_quantity":0,"shipped_quantity":1}]},"shipped_date":"2022-11-15 09:07:00","tracking_number":"AOE8269817M","tracking_url":"https://track.aftership.com/trackings?courier=alliedexpress&tracking-numbers=AOE8269817M&tracking_postal_code=4125"},{"carrier_name":"ALD","consignment_number":"consAUBW361956979_0","no_of_parcels":1,"shipment_lines":{"shipment_line":[{"order_line_id":0,"product_code":"81529","rejected_quantity":0,"shipped_quantity":1}]},"shipped_date":"2022-11-15 11:31:00","tracking_number":"AOE8273249W","tracking_url":"https://track.aftership.com/trackings?courier=alliedexpress&tracking-numbers=AOE8273249W&tracking_postal_code=2571"},{"carrier_name":"ALD","consignment_number":"consAUBW361958132_0","no_of_parcels":2,"shipment_lines":{"shipment_line":[{"order_line_id":0,"product_code":"187477","rejected_quantity":0,"shipped_quantity":1}]},"shipped_date":"2022-11-15 11:22:00","tracking_number":"AOE8273197L","tracking_url":"https://track.aftership.com/trackings?courier=alliedexpress&tracking-numbers=AOE8273197L&tracking_postal_code=2284"},{"carrier_name":"ALD","consignment_number":"consAUBW361973854_0","no_of_parcels":1,"shipment_lines":{"shipment_line":[{"order_line_id":0,"product_code":"81529","rejected_quantity":0,"shipped_quantity":1}]},"shipped_date":"2022-11-15 11:20:00","tracking_number":"AOE8273167H","tracking_url":"https://track.aftership.com/trackings?courier=alliedexpress&tracking-numbers=AOE8273167H&tracking_postal_code=2835"},{"carrier_name":"ALD","consignment_number":"consAUBW361978222_0","no_of_parcels":2,"shipment_lines":{"shipment_line":[{"order_line_id":0,"product_code":"187475","rejected_quantity":0,"shipped_quantity":1}]},"shipped_date":"2022-11-15 11:17:00","tracking_number":"AOE8273123Q","tracking_url":"https://track.aftership.com/trackings?courier=alliedexpress&tracking-numbers=AOE8273123Q&tracking_postal_code=2663"},{"carrier_name":"ALD","consignment_number":"consAUBW362026292_1","no_of_parcels":1,"shipment_lines":{"shipment_line":[{"order_line_id":1,"product_code":"229158","rejected_quantity":0,"shipped_quantity":1}]},"shipped_date":"2022-11-15 12:38:00","tracking_number":"AOE8274074D","tracking_url":"https://track.aftership.com/trackings?courier=alliedexpress&tracking-numbers=AOE8274074D&tracking_postal_code=4160"},{"carrier_name":"ALD","consignment_number":"consAUBW362099743_1","no_of_parcels":1,"shipment_lines":{"shipment_line":[{"order_line_id":0,"product_code":"121003","rejected_quantity":0,"shipped_quantity":1}]},"shipped_date":"2022-11-15 12:30:00","tracking_number":"AOE8273947L","tracking_url":"https://track.aftership.com/trackings?courier=alliedexpress&tracking-numbers=AOE8273947L&tracking_postal_code=4132"},{"carrier_name":"ALD","consignment_number":"consAUBW362178073_0","no_of_parcels":2,"shipment_lines":{"shipment_line":[{"order_line_id":0,"product_code":"81548","rejected_quantity":0,"shipped_quantity":1}]},"shipped_date":"2022-11-15 12:40:00","tracking_number":"AOE8274095R","tracking_url":"https://track.aftership.com/trackings?courier=alliedexpress&tracking-numbers=AOE8274095R&tracking_postal_code=4500"},{"carrier_name":"ALD","consignment_number":"consAUBW362205151_0","no_of_parcels":1,"shipment_lines":{"shipment_line":[{"order_line_id":0,"product_code":"81528","rejected_quantity":0,"shipped_quantity":1}]},"shipped_date":"2022-11-15 09:34:00","tracking_number":"AOE8272239A","tracking_url":"https://track.aftership.com/trackings?courier=alliedexpress&tracking-numbers=AOE8272239A&tracking_postal_code=2753"},{"carrier_name":"AUS","consignment_number":"consAUBW359946660_0","no_of_parcels":1,"shipment_lines":{"shipment_line":[{"order_line_id":0,"product_code":"121013","rejected_quantity":0,"shipped_quantity":1}]},"shipped_date":"2022-11-15 09:25:00","tracking_number":"3368R5000263","tracking_url":"https://auspost.com.au/mypost/track/#/details/3368R5000263"},{"carrier_name":"HTX","consignment_number":"consAUBW362097477_0","no_of_parcels":4,"shipment_lines":{"shipment_line":[{"order_line_id":0,"product_code":"225507","rejected_quantity":0,"shipped_quantity":1}]},"shipped_date":"2022-11-15 15:00:00","tracking_number":"GLF130894","tracking_url":"https://www.hunterexpress.com.au/home&tracking-numbers=GLF130894&tracking_postal_code=5163"}]}