{"shipment":[{"carrier_name":"ALD","consignment_number":"consAUBW374615313_0","no_of_parcels":3,"shipment_lines":{"shipment_line":[{"order_line_id":0,"product_code":"81530","rejected_quantity":0,"shipped_quantity":1}]},"shipped_date":"2023-08-14 13:16:00","tracking_number":"GFB009087","tracking_url":"https://track.aftership.com/trackings?courier=alliedexpress&tracking-numbers=GFB009087&tracking_postal_code=4280"},{"carrier_name":"ALD","consignment_number":"consAUBW374641964_0","no_of_parcels":2,"shipment_lines":{"shipment_line":[{"order_line_id":0,"product_code":"187475","rejected_quantity":0,"shipped_quantity":1}]},"shipped_date":"2023-08-14 13:37:00","tracking_number":"GFB009125","tracking_url":"https://track.aftership.com/trackings?courier=alliedexpress&tracking-numbers=GFB009125&tracking_postal_code=3550"},{"carrier_name":"ALD","consignment_number":"consAUBW374642247_0","no_of_parcels":3,"shipment_lines":{"shipment_line":[{"order_line_id":0,"product_code":"81530","rejected_quantity":0,"shipped_quantity":1}]},"shipped_date":"2023-08-14 13:34:00","tracking_number":"GFB009116","tracking_url":"https://track.aftership.com/trackings?courier=alliedexpress&tracking-numbers=GFB009116&tracking_postal_code=5158"},{"carrier_name":"ALD","consignment_number":"consAUBW374681669_0","no_of_parcels":1,"shipment_lines":{"shipment_line":[{"order_line_id":0,"product_code":"296888","rejected_quantity":0,"shipped_quantity":1}]},"shipped_date":"2023-08-14 16:19:00","tracking_number":"GFB009148","tracking_url":"https://track.aftership.com/trackings?courier=alliedexpress&tracking-numbers=GFB009148&tracking_postal_code=2328"},{"carrier_name":"ALD","consignment_number":"consAUBW374693201_0","no_of_parcels":2,"shipment_lines":{"shipment_line":[{"order_line_id":0,"product_code":"225535","rejected_quantity":0,"shipped_quantity":1}]},"shipped_date":"2023-08-14 13:15:00","tracking_number":"GFB009082","tracking_url":"https://track.aftership.com/trackings?courier=alliedexpress&tracking-numbers=GFB009082&tracking_postal_code=4518"},{"carrier_name":"ALD","consignment_number":"consAUBW374702509_0","no_of_parcels":1,"shipment_lines":{"shipment_line":[{"order_line_id":0,"product_code":"229158","rejected_quantity":0,"shipped_quantity":1}]},"shipped_date":"2023-08-14 13:18:00","tracking_number":"GFB009103","tracking_url":"https://track.aftership.com/trackings?courier=alliedexpress&tracking-numbers=GFB009103&tracking_postal_code=4560"},{"carrier_name":"ALD","consignment_number":"consAUBW374713768_0","no_of_parcels":2,"shipment_lines":{"shipment_line":[{"order_line_id":0,"product_code":"225512","rejected_quantity":0,"shipped_quantity":1}]},"shipped_date":"2023-08-14 13:18:00","tracking_number":"GFB009104","tracking_url":"https://track.aftership.com/trackings?courier=alliedexpress&tracking-numbers=GFB009104&tracking_postal_code=4300"},{"carrier_name":"ARD","consignment_number":"consAUBW374619585_0","no_of_parcels":4,"shipment_lines":{"shipment_line":[{"order_line_id":0,"product_code":"296902","rejected_quantity":0,"shipped_quantity":1}]},"shipped_date":"2023-08-14 14:39:00","tracking_number":"GFL0102840","tracking_url":"http://www.smartfreight.com/tracking&tracking-numbers=GFL0102840&tracking_postal_code=4670"},{"carrier_name":"ARD","consignment_number":"consAUBW374671200_0","no_of_parcels":1,"shipment_lines":{"shipment_line":[{"order_line_id":0,"product_code":"225478","rejected_quantity":0,"shipped_quantity":1}]},"shipped_date":"2023-08-14 12:30:00","tracking_number":"GFL0102812","tracking_url":"http://www.smartfreight.com/tracking&tracking-numbers=GFL0102812&tracking_postal_code=2084"}]}