{"shipment":[{"carrier_name":"ALLIED O/N EXP","consignment_number":"consAUBW298354256_0","no_of_parcels":1,"shipment_lines":{"shipment_line":[{"order_line_id":3,"product_code":"81529","rejected_quantity":0,"shipped_quantity":1}]},"shipped_date":"2020-12-18 15:34:00","tracking_number":"TMV145763","tracking_url":"https://track.aftership.com/trackings?courier=alliedexpress&tracking-numbers=TMV145763&tracking_postal_code=3818"},{"carrier_name":"ALLIED O/N EXP","consignment_number":"consAUBW298847899_0","no_of_parcels":1,"shipment_lines":{"shipment_line":[{"order_line_id":0,"product_code":"81529","rejected_quantity":0,"shipped_quantity":1}]},"shipped_date":"2020-12-18 14:36:00","tracking_number":"TMV145718","tracking_url":"https://track.aftership.com/trackings?courier=alliedexpress&tracking-numbers=TMV145718&tracking_postal_code=4207"},{"carrier_name":"ALLIED O/N EXP","consignment_number":"consAUBW298876869_0","no_of_parcels":1,"shipment_lines":{"shipment_line":[{"order_line_id":0,"product_code":"81528","rejected_quantity":0,"shipped_quantity":1}]},"shipped_date":"2020-12-18 14:29:00","tracking_number":"TMV145690","tracking_url":"https://track.aftership.com/trackings?courier=alliedexpress&tracking-numbers=TMV145690&tracking_postal_code=4560"},{"carrier_name":"ALLIED O/N EXP","consignment_number":"consAUBW298919869_0","no_of_parcels":3,"shipment_lines":{"shipment_line":[{"order_line_id":0,"product_code":"81530","rejected_quantity":0,"shipped_quantity":1}]},"shipped_date":"2020-12-18 14:38:00","tracking_number":"TMV145728","tracking_url":"https://track.aftership.com/trackings?courier=alliedexpress&tracking-numbers=TMV145728&tracking_postal_code=4109"},{"carrier_name":"ALLIED O/N EXP","consignment_number":"consAUBW298935201_0","no_of_parcels":1,"shipment_lines":{"shipment_line":[{"order_line_id":0,"product_code":"81529","rejected_quantity":0,"shipped_quantity":1}]},"shipped_date":"2020-12-18 12:22:00","tracking_number":"TMV145657","tracking_url":"https://track.aftership.com/trackings?courier=alliedexpress&tracking-numbers=TMV145657&tracking_postal_code=2830"},{"carrier_name":"ALLIED O/N EXP","consignment_number":"consAUBW298951629_0","no_of_parcels":1,"shipment_lines":{"shipment_line":[{"order_line_id":0,"product_code":"81529","rejected_quantity":0,"shipped_quantity":1}]},"shipped_date":"2020-12-18 12:23:00","tracking_number":"TMV145658","tracking_url":"https://track.aftership.com/trackings?courier=alliedexpress&tracking-numbers=TMV145658&tracking_postal_code=2747"},{"carrier_name":"ALLIED O/N EXP","consignment_number":"consAUBW298957411_0","no_of_parcels":1,"shipment_lines":{"shipment_line":[{"order_line_id":0,"product_code":"81529","rejected_quantity":0,"shipped_quantity":1}]},"shipped_date":"2020-12-18 12:21:00","tracking_number":"TMV145652","tracking_url":"https://track.aftership.com/trackings?courier=alliedexpress&tracking-numbers=TMV145652&tracking_postal_code=2761"},{"carrier_name":"ALLIED O/N EXP","consignment_number":"consAUBW298969999_0","no_of_parcels":1,"shipment_lines":{"shipment_line":[{"order_line_id":0,"product_code":"81529","rejected_quantity":0,"shipped_quantity":1}]},"shipped_date":"2020-12-18 15:35:00","tracking_number":"TMV145766","tracking_url":"https://track.aftership.com/trackings?courier=alliedexpress&tracking-numbers=TMV145766&tracking_postal_code=3764"},{"carrier_name":"ALLIED O/N EXP","consignment_number":"consAUBW299040520_0","no_of_parcels":1,"shipment_lines":{"shipment_line":[{"order_line_id":0,"product_code":"81529","rejected_quantity":0,"shipped_quantity":1}]},"shipped_date":"2020-12-18 10:29:00","tracking_number":"TMV145611","tracking_url":"https://track.aftership.com/trackings?courier=alliedexpress&tracking-numbers=TMV145611&tracking_postal_code=4506"},{"carrier_name":"ALLIED O/N EXP","consignment_number":"consAUBW299078045_0","no_of_parcels":1,"shipment_lines":{"shipment_line":[{"order_line_id":0,"product_code":"81529","rejected_quantity":0,"shipped_quantity":1}]},"shipped_date":"2020-12-18 08:31:00","tracking_number":"TMV145588","tracking_url":"https://track.aftership.com/trackings?courier=alliedexpress&tracking-numbers=TMV145588&tracking_postal_code=5271"}]}