{"shipment":[{"carrier_name":"ALLIED O/N EXP","consignment_number":"consAUBW335673646_0","no_of_parcels":1,"shipment_lines":{"shipment_line":[{"order_line_id":0,"product_code":"121010","rejected_quantity":0,"shipped_quantity":1}]},"shipped_date":"2021-09-21 14:20:00","tracking_number":"TMV173920","tracking_url":"https://track.aftership.com/trackings?courier=alliedexpress&tracking-numbers=TMV173920&tracking_postal_code=4070"},{"carrier_name":"ALLIED O/N EXP","consignment_number":"consAUBW336453154_1","no_of_parcels":6,"shipment_lines":{"shipment_line":[{"order_line_id":1,"product_code":"81531","rejected_quantity":0,"shipped_quantity":1}]},"shipped_date":"2021-09-21 15:37:00","tracking_number":"TMV174012","tracking_url":"https://track.aftership.com/trackings?courier=alliedexpress&tracking-numbers=TMV174012&tracking_postal_code=3250"},{"carrier_name":"ALLIED O/N EXP","consignment_number":"consAUBW336627915_0","no_of_parcels":1,"shipment_lines":{"shipment_line":[{"order_line_id":0,"product_code":"81542","rejected_quantity":0,"shipped_quantity":1}]},"shipped_date":"2021-09-21 15:35:00","tracking_number":"TMV174002","tracking_url":"https://track.aftership.com/trackings?courier=alliedexpress&tracking-numbers=TMV174002&tracking_postal_code=3915"},{"carrier_name":"ALLIED O/N EXP","consignment_number":"consAUBW336708223_0","no_of_parcels":1,"shipment_lines":{"shipment_line":[{"order_line_id":0,"product_code":"121010","rejected_quantity":0,"shipped_quantity":1}]},"shipped_date":"2021-09-21 16:13:00","tracking_number":"TMV174034","tracking_url":"https://track.aftership.com/trackings?courier=alliedexpress&tracking-numbers=TMV174034&tracking_postal_code=7018"},{"carrier_name":"ALLIED O/N EXP","consignment_number":"consAUBW336731917_0","no_of_parcels":1,"shipment_lines":{"shipment_line":[{"order_line_id":0,"product_code":"81528","rejected_quantity":0,"shipped_quantity":1}]},"shipped_date":"2021-09-21 15:33:00","tracking_number":"TMV173994","tracking_url":"https://track.aftership.com/trackings?courier=alliedexpress&tracking-numbers=TMV173994&tracking_postal_code=3730"},{"carrier_name":"ALLIED O/N EXP","consignment_number":"consAUBW336735920_0","no_of_parcels":2,"shipment_lines":{"shipment_line":[{"order_line_id":0,"product_code":"81546","rejected_quantity":0,"shipped_quantity":1}]},"shipped_date":"2021-09-21 14:17:00","tracking_number":"TMV173905","tracking_url":"https://track.aftership.com/trackings?courier=alliedexpress&tracking-numbers=TMV173905&tracking_postal_code=4055"},{"carrier_name":"ALLIED O/N EXP","consignment_number":"consAUBW336779304_0","no_of_parcels":6,"shipment_lines":{"shipment_line":[{"order_line_id":0,"product_code":"81531","rejected_quantity":0,"shipped_quantity":1}]},"shipped_date":"2021-09-21 14:20:00","tracking_number":"TMV173919","tracking_url":"https://track.aftership.com/trackings?courier=alliedexpress&tracking-numbers=TMV173919&tracking_postal_code=4065"},{"carrier_name":"ALLIED O/N EXP","consignment_number":"consAUBW336834345_0","no_of_parcels":6,"shipment_lines":{"shipment_line":[{"order_line_id":0,"product_code":"131122","rejected_quantity":0,"shipped_quantity":1}]},"shipped_date":"2021-09-21 14:19:00","tracking_number":"TMV173915","tracking_url":"https://track.aftership.com/trackings?courier=alliedexpress&tracking-numbers=TMV173915&tracking_postal_code=4113"},{"carrier_name":"ALLIED O/N EXP","consignment_number":"consAUBW336856465_0","no_of_parcels":1,"shipment_lines":{"shipment_line":[{"order_line_id":0,"product_code":"121010","rejected_quantity":0,"shipped_quantity":1}]},"shipped_date":"2021-09-21 14:19:00","tracking_number":"TMV173912","tracking_url":"https://track.aftership.com/trackings?courier=alliedexpress&tracking-numbers=TMV173912&tracking_postal_code=4556"},{"carrier_name":"ALLIED O/N EXP","consignment_number":"consAUBW336918909_0","no_of_parcels":1,"shipment_lines":{"shipment_line":[{"order_line_id":0,"product_code":"81542","rejected_quantity":0,"shipped_quantity":1}]},"shipped_date":"2021-09-21 12:33:00","tracking_number":"TMV173875","tracking_url":"https://track.aftership.com/trackings?courier=alliedexpress&tracking-numbers=TMV173875&tracking_postal_code=6056"},{"carrier_name":"AUSTRALIA POST","consignment_number":"consAUBW337003400_0","no_of_parcels":1,"shipment_lines":{"shipment_line":[{"order_line_id":1,"product_code":"121013","rejected_quantity":0,"shipped_quantity":1}]},"shipped_date":"2021-09-21 12:58:00","tracking_number":"89U2046829","tracking_url":"https://auspost.com.au/mypost/track/#/details/89U2046829"}]}